{
    "title": "快速开始",
    "items": [
        {
            "title": "概述",
            "urls": [
                "/${VERSION}/getting-started/rainbond-overview.html"
            ]
        },
        {
            "title": "一键安装",
            "urls": [
                "/${VERSION}/getting-started/before-installation.html",
                "/${VERSION}/getting-started/online-installation.html"
            ]
        },
        {
            "title": "公有云试用",
            "urls": [
                "/${VERSION}/getting-started/public-cloud-brief.html"
            ]
        }
    ]
}
